ugot_broadcast_message.py
ugot_broadcast_message_pb2/__init__.py
ugot_broadcast_message_pb2/ugot_broadcast_message_pb2_gen1.py
ugot_broadcast_message_pb2/ugot_broadcast_message_pb2_gen2.py
uGot_Broadcast_message-0.0.2.dist-info/LICENSE
uGot_Broadcast_message-0.0.2.dist-info/METADATA
uGot_Broadcast_message-0.0.2.dist-info/WHEEL
uGot_Broadcast_message-0.0.2.dist-info/top_level.txt
uGot_Broadcast_message-0.0.2.dist-info/RECORD
